[
{
  "model": "intake.applicant",
  "pk": 420,
  "fields": {
    "visitor": null
  }
},
{
  "model": "intake.applicant",
  "pk": 421,
  "fields": {
    "visitor": null
  }
},
{
  "model": "intake.formsubmission",
  "pk": 419,
  "fields": {
    "applicant": 420,
    "duplicate_set": null,
    "answers": {
      "monthly_income": 3995,
      "last_name": "Haynes",
      "rap_outside_sf": "no",
      "how_did_you_hear": "from work",
      "has_children": "yes",
      "understands_limits": "yes",
      "currently_employed": "no",
      "phone_number": "2076393075",
      "household_size": 4,
      "when_probation_or_parole": "2018",
      "email": "qdrake@gmail.com",
      "reasons_for_applying": [
        "background_check",
        "lost_job",
        "housing"
      ],
      "serving_sentence": "no",
      "where_probation_or_parole": "Solano County",
      "when_where_outside_sf": "",
      "on_public_benefits": "yes",
      "is_married": "no",
      "us_citizen": "yes",
      "is_veteran": "no",
      "dob": {
        "year": "1973",
        "month": "10",
        "day": "27"
      },
      "declaration_letter_life_changes": "Nihil ex praesentium minima cumque est repudiandae cupiditate. Vitae vero non sunt vero nesciunt itaque assumenda vitae. Aut dolorum quasi explicabo. Tempora possimus perferendis vitae reprehenderit.",
      "contact_preferences": [
        "prefers_voicemail",
        "prefers_email",
        "prefers_sms",
        "prefers_snailmail"
      ],
      "declaration_letter_activities": "Exercitationem dicta possimus aliquam officia. Voluptatibus sint eveniet eligendi ipsum id ut. Minima cupiditate adipisci cupiditate quo.",
      "income_source": "a job",
      "address": {
        "street": "1611 Andrew Heights",
        "state": "IN",
        "city": "Michelleville",
        "zip": "91312"
      },
      "on_probation_parole": "yes",
      "first_name": "Daniel",
      "alternate_phone_number": "2648390736",
      "being_charged": "no",
      "declaration_letter_goals": "Totam exercitationem ratione quisquam ut mollitia impedit. Fuga nihil accusantium repellendus aliquam.",
      "consent_to_represent": "yes",
      "declaration_letter_intro": "Nam velit soluta dolores iusto aliquid recusandae libero cum. Ex magni saepe perferendis doloremque culpa nihil possimus fugit. Eius quas quisquam est dolor incidunt alias provident. Laborum ea veniam placeat laudantium.",
      "declaration_letter_why": "Vero illo vel nam enim saepe necessitatibus corrupti. Suscipit officiis provident cupiditate magnam. Odio odio repudiandae tempora mollitia eligendi ullam dignissimos.",
      "owes_court_fees": "no",
      "monthly_expenses": 2000,
      "additional_information": "I want help",
      "reduced_probation": "no",
      "middle_name": "Maria"
    },
    "old_uuid": "ac48e301721c40929b3ee289652a7bf7",
    "anonymous_name": "Calm Koala",
    "date_received": "2017-01-23T09:34:12-08:00"
  }
},
{
  "model": "intake.formsubmission",
  "pk": 420,
  "fields": {
    "applicant": 421,
    "duplicate_set": null,
    "answers": {
      "monthly_income": 6983,
      "last_name": "Barrett",
      "rap_outside_sf": "no",
      "how_did_you_hear": "from work",
      "has_children": "yes",
      "understands_limits": "yes",
      "currently_employed": "no",
      "phone_number": "2261549129",
      "household_size": 3,
      "when_probation_or_parole": "2018",
      "email": "umartinez@gmail.com",
      "reasons_for_applying": [
        "background_check",
        "lost_job",
        "housing"
      ],
      "serving_sentence": "no",
      "where_probation_or_parole": "Solano County",
      "when_where_outside_sf": "",
      "on_public_benefits": "yes",
      "is_married": "no",
      "us_citizen": "yes",
      "is_veteran": "yes",
      "dob": {
        "year": "1998",
        "month": "12",
        "day": "5"
      },
      "declaration_letter_life_changes": "Dolor minus amet dignissimos aspernatur delectus. Magni tenetur facilis et ratione. Odit voluptates numquam quod dignissimos est. Modi voluptas dignissimos labore iure magni at.",
      "contact_preferences": [
        "prefers_voicemail",
        "prefers_email",
        "prefers_snailmail",
        "prefers_sms"
      ],
      "declaration_letter_activities": "Voluptatum mollitia nihil quas eum labore quo hic repellat. Non velit sint occaecati unde. Nisi ducimus magni sint dicta ipsum debitis tempore.",
      "income_source": "a job",
      "address": {
        "street": "165 Jordan Stream Apt. 867",
        "state": "NC",
        "city": "Christopherhaven",
        "zip": "08993"
      },
      "on_probation_parole": "yes",
      "first_name": "Eugene",
      "alternate_phone_number": "2517321299",
      "being_charged": "no",
      "declaration_letter_goals": "Necessitatibus suscipit iusto optio esse incidunt qui natus consectetur. Voluptatem unde dolore libero quisquam. Esse adipisci explicabo dolorem repellat. Repudiandae sint blanditiis delectus odio.",
      "consent_to_represent": "yes",
      "declaration_letter_intro": "Maiores doloremque odit alias ab. Facilis itaque inventore dolore ad. Atque distinctio quo dolorum esse. Velit dolorum natus quos eum facere aut. Architecto ipsa corrupti dolor optio laudantium.",
      "declaration_letter_why": "Magni blanditiis amet nesciunt dolor. Possimus fugit ipsam qui dolor deleniti nihil possimus veritatis. Facilis officiis aut soluta laboriosam numquam voluptatem nostrum.",
      "owes_court_fees": "yes",
      "monthly_expenses": 2000,
      "additional_information": "I want help",
      "reduced_probation": "no",
      "middle_name": "Gary"
    },
    "old_uuid": "dc8561f32ea54fc49c6b429694dc0e4a",
    "anonymous_name": "Pink Island",
    "date_received": "2017-01-21T08:03:11-08:00"
  }
},
{
  "model": "intake.application",
  "pk": 240,
  "fields": {
    "organization": [
      "Santa Clara County Public Defender"
    ],
    "form_submission": 419
  }
},
{
  "model": "intake.application",
  "pk": 241,
  "fields": {
    "organization": [
      "Santa Clara County Public Defender"
    ],
    "form_submission": 420
  }
}
]
