[
{
  "model": "intake.visitor",
  "pk": 7,
  "fields": {
    "first_visit": "2017-03-28T00:59:56.200Z",
    "source": "share",
    "referrer": "http://bajoradefender.org/services/clean-slate/",
    "ip_address": "48.104.186.127"
  }
},
{
  "model": "intake.visitor",
  "pk": 8,
  "fields": {
    "first_visit": "2017-03-28T00:59:56.219Z",
    "source": "share",
    "referrer": "http://bajoradefender.org/services/clean-slate/",
    "ip_address": "48.104.186.127"
  }
},
{
  "model": "intake.applicant",
  "pk": 7,
  "fields": {
    "visitor": 7
  }
},
{
  "model": "intake.applicant",
  "pk": 8,
  "fields": {
    "visitor": 8
  }
},
{
  "model": "intake.formsubmission",
  "pk": 7,
  "fields": {
    "applicant": 7,
    "duplicate_set": null,
    "answers": {
      "contact_preferences": [
        "prefers_sms",
        "prefers_email"
      ],
      "first_name": "Thomas",
      "middle_name": "Erik",
      "last_name": "Stanley",
      "aliases": "Dennis Galloway MD",
      "phone_number": "8314207603",
      "alternate_phone_number": "8314207603",
      "email": "bgolder+testing@codeforamerica.org",
      "address": {
        "street": "2070 David Ridges",
        "city": "North Bernard",
        "state": "FM",
        "zip": "16146"
      },
      "dob": {
        "month": "12",
        "day": "16",
        "year": "1986"
      },
      "driver_license_or_id": "D8284429",
      "last_four": "2356",
      "case_number": "C2541-264",
      "us_citizen": "yes",
      "being_charged": "no",
      "serving_sentence": "no",
      "on_probation_parole": "yes",
      "where_probation_or_parole": "Yolo County",
      "when_probation_or_parole": "2018",
      "monthly_income": 1762,
      "dependents": 2,
      "reasons_for_applying": [
        "background_check",
        "lost_job",
        "housing"
      ],
      "how_did_you_hear": "from work",
      "additional_information": "I want help",
      "understands_limits": "yes",
      "consent_to_represent": "yes"
    },
    "first_name": "Thomas",
    "last_name": "Stanley",
    "dob": null,
    "ssn": "",
    "last_four": "2356",
    "drivers_license_or_id": "",
    "case_number": "C2541-264",
    "phone_number": "8314207603",
    "alternate_phone_number": "8314207603",
    "email": "bgolder+testing@codeforamerica.org",
    "old_uuid": "d1d76492ecf7434db51391f898154a57",
    "anonymous_name": "Invisible Planet",
    "date_received": "2017-03-21T15:29:02-07:00"
  }
},
{
  "model": "intake.formsubmission",
  "pk": 8,
  "fields": {
    "applicant": 8,
    "duplicate_set": null,
    "answers": {
      "contact_preferences": [
        "prefers_email",
        "prefers_sms"
      ],
      "first_name": "Deborah",
      "middle_name": "Emily",
      "last_name": "Peterson",
      "aliases": "Samuel Strickland",
      "phone_number": "8314207603",
      "alternate_phone_number": "8314207603",
      "email": "bgolder+testing@codeforamerica.org",
      "address": {
        "street": "45547 Burgess Flat",
        "city": "Port Christine",
        "state": "ID",
        "zip": "94603"
      },
      "dob": {
        "month": "9",
        "day": "28",
        "year": "1959"
      },
      "driver_license_or_id": "D6044870",
      "last_four": "9539",
      "case_number": "C3538-546",
      "us_citizen": "yes",
      "being_charged": "no",
      "serving_sentence": "no",
      "on_probation_parole": "yes",
      "where_probation_or_parole": "Yolo County",
      "when_probation_or_parole": "2018",
      "monthly_income": 3467,
      "dependents": 1,
      "reasons_for_applying": [
        "background_check",
        "lost_job",
        "housing"
      ],
      "how_did_you_hear": "from work",
      "additional_information": "I want help",
      "understands_limits": "yes",
      "consent_to_represent": "yes"
    },
    "first_name": "Deborah",
    "last_name": "Peterson",
    "dob": null,
    "ssn": "",
    "last_four": "9539",
    "drivers_license_or_id": "",
    "case_number": "C3538-546",
    "phone_number": "8314207603",
    "alternate_phone_number": "8314207603",
    "email": "bgolder+testing@codeforamerica.org",
    "old_uuid": "25cfc147dd4f4931ad79f47e2257bbd7",
    "anonymous_name": "Indigo Flounder",
    "date_received": "2017-03-26T20:23:42-07:00"
  }
},
{
  "model": "intake.application",
  "pk": 7,
  "fields": {
    "created": "2017-03-21T22:29:02Z",
    "updated": "2017-03-28T00:59:56.211Z",
    "organization": [
      "Fresno County Public Defender"
    ],
    "form_submission": 7,
    "was_transferred_out": false
  }
},
{
  "model": "intake.application",
  "pk": 8,
  "fields": {
    "created": "2017-03-27T03:23:42Z",
    "updated": "2017-03-28T00:59:56.234Z",
    "organization": [
      "Fresno County Public Defender"
    ],
    "form_submission": 8,
    "was_transferred_out": false
  }
},
{
  "model": "intake.statusupdate",
  "pk": 7,
  "fields": {
    "created": "2017-03-28T00:59:56.886Z",
    "updated": "2017-03-28T00:59:56.899Z",
    "status_type": 7,
    "additional_information": "We may be able to get a fee waived for you",
    "author": [
      "fresno_pubdef_user"
    ],
    "application": 7,
    "other_next_step": "Come to our Walk-In Clinic",
    "next_steps": [
      1
    ]
  }
},
{
  "model": "intake.statusupdate",
  "pk": 8,
  "fields": {
    "created": "2017-03-28T00:59:56.909Z",
    "updated": "2017-03-28T00:59:56.920Z",
    "status_type": 1,
    "additional_information": "We may be able to get a fee waived for you",
    "author": [
      "fresno_pubdef_user"
    ],
    "application": 8,
    "other_next_step": "Come to our Walk-In Clinic",
    "next_steps": [
      1
    ]
  }
},
{
  "model": "intake.statusnotification",
  "pk": 7,
  "fields": {
    "status_update": 7,
    "contact_info": {
      "email": "bgolder+borg@codeforamerica.org"
    },
    "base_message": "Resistance is futile",
    "sent_message": "Live long and prosper",
    "created": "2017-03-28T00:59:56.888Z"
  }
},
{
  "model": "intake.statusnotification",
  "pk": 8,
  "fields": {
    "status_update": 8,
    "contact_info": {
      "email": "bgolder+borg@codeforamerica.org"
    },
    "base_message": "Resistance is futile",
    "sent_message": "Live long and prosper",
    "created": "2017-03-28T00:59:56.911Z"
  }
}
]
