[
{
  "model": "intake.visitor",
  "pk": 19,
  "fields": {
    "first_visit": "2017-03-28T00:59:56.455Z",
    "source": "share",
    "referrer": "http://bajoradefender.org/services/clean-slate/",
    "ip_address": "48.104.186.127"
  }
},
{
  "model": "intake.visitor",
  "pk": 20,
  "fields": {
    "first_visit": "2017-03-28T00:59:56.478Z",
    "source": "share",
    "referrer": "http://bajoradefender.org/services/clean-slate/",
    "ip_address": "48.104.186.127"
  }
},
{
  "model": "intake.applicant",
  "pk": 19,
  "fields": {
    "visitor": 19
  }
},
{
  "model": "intake.applicant",
  "pk": 20,
  "fields": {
    "visitor": 20
  }
},
{
  "model": "intake.formsubmission",
  "pk": 19,
  "fields": {
    "applicant": 19,
    "duplicate_set": null,
    "answers": {
      "contact_preferences": [
        "prefers_email",
        "prefers_sms"
      ],
      "first_name": "Tiffany",
      "middle_name": "Jay",
      "last_name": "Lewis",
      "phone_number": "8314207603",
      "alternate_phone_number": "8314207603",
      "email": "bgolder+testing@codeforamerica.org",
      "address": {
        "street": "983 Philip Plaza",
        "city": "Longmouth",
        "state": "WY",
        "zip": "13412"
      },
      "dob": {
        "month": "3",
        "day": "28",
        "year": "1990"
      },
      "us_citizen": "yes",
      "being_charged": "no",
      "serving_sentence": "no",
      "on_probation_parole": "yes",
      "where_probation_or_parole": "Yolo County",
      "when_probation_or_parole": "2018",
      "monthly_income": 3079,
      "reasons_for_applying": [
        "lost_job",
        "homeless"
      ],
      "how_did_you_hear": "from work",
      "additional_information": "I want help",
      "understands_limits": "yes",
      "consent_to_represent": "yes"
    },
    "first_name": "Tiffany",
    "last_name": "Lewis",
    "dob": null,
    "ssn": "",
    "last_four": "",
    "drivers_license_or_id": "",
    "case_number": "",
    "phone_number": "8314207603",
    "alternate_phone_number": "8314207603",
    "email": "bgolder+testing@codeforamerica.org",
    "old_uuid": "9f3ab9ca82834d639f2c951b9ebb1814",
    "anonymous_name": "Exuberant Pulsar",
    "date_received": "2017-03-20T03:36:42-07:00"
  }
},
{
  "model": "intake.formsubmission",
  "pk": 20,
  "fields": {
    "applicant": 20,
    "duplicate_set": null,
    "answers": {
      "contact_preferences": [
        "prefers_sms",
        "prefers_email"
      ],
      "first_name": "Kenneth",
      "middle_name": "Scott",
      "last_name": "Sanchez",
      "phone_number": "8314207603",
      "alternate_phone_number": "8314207603",
      "email": "bgolder+testing@codeforamerica.org",
      "address": {
        "street": "822 Lori Ramp Suite 442",
        "city": "Taylorborough",
        "state": "NM",
        "zip": "54170"
      },
      "dob": {
        "month": "3",
        "day": "1",
        "year": "1997"
      },
      "us_citizen": "yes",
      "being_charged": "no",
      "serving_sentence": "no",
      "on_probation_parole": "yes",
      "where_probation_or_parole": "Yolo County",
      "when_probation_or_parole": "2018",
      "monthly_income": 2982,
      "reasons_for_applying": [
        "lost_job",
        "homeless"
      ],
      "how_did_you_hear": "from work",
      "additional_information": "I want help",
      "understands_limits": "yes",
      "consent_to_represent": "yes"
    },
    "first_name": "Kenneth",
    "last_name": "Sanchez",
    "dob": null,
    "ssn": "",
    "last_four": "",
    "drivers_license_or_id": "",
    "case_number": "",
    "phone_number": "8314207603",
    "alternate_phone_number": "8314207603",
    "email": "bgolder+testing@codeforamerica.org",
    "old_uuid": "9ffe6a3bbc734359a7c18ec4b6b4390b",
    "anonymous_name": "Humming Llama",
    "date_received": "2017-03-17T01:54:32-07:00"
  }
},
{
  "model": "intake.application",
  "pk": 19,
  "fields": {
    "created": "2017-03-20T10:36:42Z",
    "updated": "2017-03-28T00:59:56.469Z",
    "organization": [
      "Santa Cruz County Public Defender"
    ],
    "form_submission": 19,
    "was_transferred_out": false
  }
},
{
  "model": "intake.application",
  "pk": 20,
  "fields": {
    "created": "2017-03-17T08:54:32Z",
    "updated": "2017-03-28T00:59:56.489Z",
    "organization": [
      "Santa Cruz County Public Defender"
    ],
    "form_submission": 20,
    "was_transferred_out": false
  }
},
{
  "model": "intake.statusupdate",
  "pk": 19,
  "fields": {
    "created": "2017-03-28T00:59:57.150Z",
    "updated": "2017-03-28T00:59:57.159Z",
    "status_type": 5,
    "additional_information": "We may be able to get a fee waived for you",
    "author": [
      "santa_cruz_pubdef_user"
    ],
    "application": 19,
    "other_next_step": "Come to our Walk-In Clinic",
    "next_steps": [
      1
    ]
  }
},
{
  "model": "intake.statusupdate",
  "pk": 20,
  "fields": {
    "created": "2017-03-28T00:59:57.167Z",
    "updated": "2017-03-28T00:59:57.176Z",
    "status_type": 6,
    "additional_information": "We may be able to get a fee waived for you",
    "author": [
      "santa_cruz_pubdef_user"
    ],
    "application": 20,
    "other_next_step": "Come to our Walk-In Clinic",
    "next_steps": [
      1
    ]
  }
},
{
  "model": "intake.statusnotification",
  "pk": 19,
  "fields": {
    "status_update": 19,
    "contact_info": {
      "email": "bgolder+borg@codeforamerica.org"
    },
    "base_message": "Resistance is futile",
    "sent_message": "Live long and prosper",
    "created": "2017-03-28T00:59:57.152Z"
  }
},
{
  "model": "intake.statusnotification",
  "pk": 20,
  "fields": {
    "status_update": 20,
    "contact_info": {
      "email": "bgolder+borg@codeforamerica.org"
    },
    "base_message": "Resistance is futile",
    "sent_message": "Live long and prosper",
    "created": "2017-03-28T00:59:57.169Z"
  }
}
]
