[
{
  "model": "intake.visitor",
  "pk": 75,
  "fields": {
    "first_visit": "2017-04-04T23:26:38.188Z",
    "source": "share",
    "referrer": "http://bajoradefender.org/services/clean-slate/",
    "ip_address": "48.104.186.127"
  }
},
{
  "model": "intake.visitor",
  "pk": 76,
  "fields": {
    "first_visit": "2017-04-04T23:26:38.204Z",
    "source": "share",
    "referrer": "http://bajoradefender.org/services/clean-slate/",
    "ip_address": "48.104.186.127"
  }
},
{
  "model": "intake.applicant",
  "pk": 72,
  "fields": {
    "visitor": 75
  }
},
{
  "model": "intake.applicant",
  "pk": 73,
  "fields": {
    "visitor": 76
  }
},
{
  "model": "intake.formsubmission",
  "pk": 72,
  "fields": {
    "applicant": 72,
    "duplicate_set": null,
    "answers": {
      "owes_court_fees": "no",
      "first_name": "Natasha",
      "rap_outside_sf": "no",
      "understands_limits": "yes",
      "last_name": "Griffin",
      "has_suspended_license": "no",
      "owns_home": "yes",
      "contact_preferences": [
        "prefers_sms"
      ],
      "on_public_benefits": "yes",
      "phone_number": "8314207603",
      "middle_name": "Becky",
      "serving_sentence": "no",
      "reduced_probation": "not_applicable",
      "when_where_outside_sf": "",
      "alternate_phone_number": "8314207603",
      "monthly_income": 3001,
      "on_probation_parole": "yes",
      "finished_half_probation": "not_applicable",
      "us_citizen": "yes",
      "how_did_you_hear": "from work",
      "additional_information": "I want help",
      "email": "bgolder+testing@codeforamerica.org",
      "address": {
        "state": "NH",
        "city": "West April",
        "zip": "10979",
        "street": "60261 Conway Ports Suite 013"
      },
      "being_charged": "no",
      "consent_to_represent": "yes",
      "preferred_pronouns": "she",
      "household_size": 4,
      "dob": {
        "month": "11",
        "day": "31",
        "year": "1979"
      }
    },
    "first_name": "Natasha",
    "last_name": "Griffin",
    "dob": null,
    "ssn": "",
    "last_four": "",
    "drivers_license_or_id": "",
    "case_number": "",
    "phone_number": "8314207603",
    "alternate_phone_number": "8314207603",
    "email": "bgolder+testing@codeforamerica.org",
    "old_uuid": "03642fdbb9764a5d815f36d9c37e2736",
    "anonymous_name": "Vermillion Mushroom",
    "date_received": "2017-04-03T07:40:46-07:00"
  }
},
{
  "model": "intake.formsubmission",
  "pk": 73,
  "fields": {
    "applicant": 73,
    "duplicate_set": null,
    "answers": {
      "owes_court_fees": "no",
      "first_name": "Gary",
      "rap_outside_sf": "yes",
      "understands_limits": "yes",
      "last_name": "Davis",
      "has_suspended_license": "no",
      "owns_home": "yes",
      "contact_preferences": [
        "prefers_sms",
        "prefers_email"
      ],
      "on_public_benefits": "yes",
      "phone_number": "8314207603",
      "middle_name": "Daniel",
      "serving_sentence": "no",
      "reduced_probation": "not_applicable",
      "when_where_outside_sf": "",
      "alternate_phone_number": "8314207603",
      "monthly_income": 3001,
      "on_probation_parole": "yes",
      "finished_half_probation": "not_applicable",
      "us_citizen": "yes",
      "how_did_you_hear": "from work",
      "additional_information": "I want help",
      "email": "bgolder+testing@codeforamerica.org",
      "address": {
        "state": "IN",
        "city": "Thompsonmouth",
        "zip": "10898",
        "street": "7182 Cindy Spur"
      },
      "being_charged": "no",
      "consent_to_represent": "yes",
      "preferred_pronouns": "she",
      "household_size": 4,
      "dob": {
        "month": "3",
        "day": "14",
        "year": "2000"
      }
    },
    "first_name": "Gary",
    "last_name": "Davis",
    "dob": null,
    "ssn": "",
    "last_four": "",
    "drivers_license_or_id": "",
    "case_number": "",
    "phone_number": "8314207603",
    "alternate_phone_number": "8314207603",
    "email": "bgolder+testing@codeforamerica.org",
    "old_uuid": "237deb58e929466d9223a850d65efb56",
    "anonymous_name": "Aqua Armadillo",
    "date_received": "2017-03-22T03:06:35-07:00"
  }
},
{
  "model": "intake.application",
  "pk": 102,
  "fields": {
    "created": "2017-04-03T14:40:46Z",
    "updated": "2017-04-04T23:26:38.198Z",
    "organization": [
      "East Bay Community Law Center"
    ],
    "form_submission": 72,
    "was_transferred_out": false
  }
},
{
  "model": "intake.application",
  "pk": 103,
  "fields": {
    "created": "2017-03-22T10:06:35Z",
    "updated": "2017-04-04T23:26:38.214Z",
    "organization": [
      "East Bay Community Law Center"
    ],
    "form_submission": 73,
    "was_transferred_out": false
  }
},
{
  "model": "intake.statusupdate",
  "pk": 107,
  "fields": {
    "created": "2017-04-04T23:26:38.860Z",
    "updated": "2017-04-04T23:26:38.867Z",
    "status_type": 4,
    "additional_information": "We may be able to get a fee waived for you",
    "author": [
      "ebclc_user"
    ],
    "application": 102,
    "other_next_step": "Come to our Walk-In Clinic",
    "next_steps": [
      1
    ]
  }
},
{
  "model": "intake.statusupdate",
  "pk": 108,
  "fields": {
    "created": "2017-04-04T23:26:38.874Z",
    "updated": "2017-04-04T23:26:38.881Z",
    "status_type": 5,
    "additional_information": "We may be able to get a fee waived for you",
    "author": [
      "ebclc_user"
    ],
    "application": 103,
    "other_next_step": "Come to our Walk-In Clinic",
    "next_steps": [
      1
    ]
  }
},
{
  "model": "intake.statusnotification",
  "pk": 107,
  "fields": {
    "status_update": 107,
    "contact_info": {
      "email": "bgolder+borg@codeforamerica.org"
    },
    "base_message": "Resistance is futile",
    "sent_message": "Live long and prosper",
    "created": "2017-04-04T23:26:38.862Z"
  }
},
{
  "model": "intake.statusnotification",
  "pk": 108,
  "fields": {
    "status_update": 108,
    "contact_info": {
      "email": "bgolder+borg@codeforamerica.org"
    },
    "base_message": "Resistance is futile",
    "sent_message": "Live long and prosper",
    "created": "2017-04-04T23:26:38.875Z"
  }
}
]
