[
{
  "model": "intake.applicant",
  "pk": 625,
  "fields": {
    "visitor": null
  }
},
{
  "model": "intake.applicant",
  "pk": 626,
  "fields": {
    "visitor": null
  }
},
{
  "model": "intake.formsubmission",
  "pk": 824,
  "fields": {
    "applicant": 625,
    "duplicate_set": null,
    "answers": {
      "dob": {
        "month": "5",
        "year": "1969",
        "day": "18"
      },
      "us_citizen": "yes",
      "how_did_you_hear": "",
      "monthly_income": 4311,
      "income_source": "a job",
      "phone_number": "2280869525",
      "last_name": "Francis",
      "middle_name": "",
      "additional_information": "",
      "serving_sentence": "no",
      "consent_to_represent": "yes",
      "monthly_expenses": 247,
      "on_probation_parole": "no",
      "understands_limits": "yes",
      "first_name": "Julie",
      "currently_employed": "yes",
      "email": "douglasrichardson@hotmail.com",
      "address": {
        "state": "MP",
        "city": "West Laurie",
        "street": "958 Julie Road Apt. 314",
        "zip": "39119"
      },
      "contact_preferences": [
        "prefers_voicemail",
        "prefers_sms",
        "prefers_email"
      ]
    },
    "old_uuid": "1ee72a4cb0e94865bdbb9960676ff8e1",
    "anonymous_name": "Shimmering Swan",
    "date_received": "2017-01-15T20:49:02-08:00"
  }
},
{
  "model": "intake.formsubmission",
  "pk": 825,
  "fields": {
    "applicant": 626,
    "duplicate_set": null,
    "answers": {
      "dob": {
        "month": "3",
        "year": "1997",
        "day": "10"
      },
      "us_citizen": "yes",
      "how_did_you_hear": "",
      "monthly_income": 1653,
      "income_source": "a job",
      "phone_number": "2409198044",
      "last_name": "Phelps",
      "middle_name": "",
      "additional_information": "",
      "serving_sentence": "no",
      "consent_to_represent": "yes",
      "monthly_expenses": 502,
      "on_probation_parole": "no",
      "understands_limits": "yes",
      "first_name": "Dawn",
      "currently_employed": "no",
      "email": "mcdanielsarah@hotmail.com",
      "address": {
        "state": "GU",
        "city": "North Jamesborough",
        "street": "1108 Jacobson Land Apt. 193",
        "zip": "46943"
      },
      "contact_preferences": [
        "prefers_sms",
        "prefers_snailmail"
      ]
    },
    "old_uuid": "450151e844794bc88ca7bb1d5f2f56b0",
    "anonymous_name": "Stupendous Sequoia",
    "date_received": "2017-01-23T18:28:56-08:00"
  }
},
{
  "model": "intake.application",
  "pk": 515,
  "fields": {
    "organization": [
      "Contra Costa Public Defender"
    ],
    "form_submission": 824
  }
},
{
  "model": "intake.application",
  "pk": 516,
  "fields": {
    "organization": [
      "Contra Costa Public Defender"
    ],
    "form_submission": 825
  }
},
{
  "model": "intake.statusupdate",
  "pk": 209,
  "fields": {
    "created": "2017-01-27T19:14:32.910Z",
    "updated": "2017-01-27T19:14:32.921Z",
    "status_type": 1,
    "additional_information": "We may be able to get a fee waived for you",
    "author": [
      "cc_pubdef_user"
    ],
    "application": 515,
    "other_next_step": "Come to our Walk-In Clinic",
    "next_steps": [
      1
    ]
  }
},
{
  "model": "intake.statusupdate",
  "pk": 210,
  "fields": {
    "created": "2017-01-27T19:14:32.940Z",
    "updated": "2017-01-27T19:14:32.947Z",
    "status_type": 2,
    "additional_information": "We may be able to get a fee waived for you",
    "author": [
      "cc_pubdef_user"
    ],
    "application": 516,
    "other_next_step": "Come to our Walk-In Clinic",
    "next_steps": [
      1
    ]
  }
},
{
  "model": "intake.statusnotification",
  "pk": 82,
  "fields": {
    "status_update": 209,
    "contact_info": {
      "email": "bgolder+borg@codeforamerica.org"
    },
    "base_message": "Resistance is futile",
    "sent_message": "Live long and prosper",
    "created": "2017-01-27T19:14:33.714Z"
  }
},
{
  "model": "intake.statusnotification",
  "pk": 83,
  "fields": {
    "status_update": 210,
    "contact_info": {
      "email": "bgolder+borg@codeforamerica.org"
    },
    "base_message": "Resistance is futile",
    "sent_message": "Live long and prosper",
    "created": "2017-01-27T19:14:33.720Z"
  }
}
]
