[
{
  "model": "intake.visitor",
  "pk": 74,
  "fields": {
    "first_visit": "2017-04-25T01:52:08.819Z",
    "source": "share",
    "referrer": "http://bajoradefender.org/services/clean-slate/",
    "ip_address": "48.104.186.127"
  }
},
{
  "model": "intake.visitor",
  "pk": 75,
  "fields": {
    "first_visit": "2017-04-25T01:52:08.842Z",
    "source": "share",
    "referrer": "http://bajoradefender.org/services/clean-slate/",
    "ip_address": "48.104.186.127"
  }
},
{
  "model": "intake.applicant",
  "pk": 74,
  "fields": {
    "visitor": 74
  }
},
{
  "model": "intake.applicant",
  "pk": 75,
  "fields": {
    "visitor": 75
  }
},
{
  "model": "intake.formsubmission",
  "pk": 73,
  "fields": {
    "applicant": 74,
    "duplicate_set": null,
    "answers": {
      "contact_preferences": [
        "prefers_email"
      ],
      "first_name": "Jesse",
      "middle_name": "Theresa",
      "last_name": "Davis",
      "aliases": "Taylor Brown",
      "phone_number": "8314207603",
      "alternate_phone_number": "8314207603",
      "email": "cmrtestuser@gmail.com",
      "address": {
        "street": "099 Sawyer Station",
        "city": "Gomezmouth",
        "state": "OR",
        "zip": "38721"
      },
      "dob": {
        "month": "4",
        "day": "26",
        "year": "1967"
      },
      "driver_license_or_id": "D5434541",
      "last_four": "1133",
      "case_number": "C4158-116",
      "us_citizen": "no",
      "being_charged": "no",
      "serving_sentence": "no",
      "on_probation_parole": "yes",
      "where_probation_or_parole": "Yolo County",
      "when_probation_or_parole": "2018",
      "monthly_income": 3625,
      "dependents": 2,
      "reasons_for_applying": [
        "background_check",
        "lost_job",
        "housing"
      ],
      "how_did_you_hear": "from work",
      "additional_information": "I want help",
      "understands_limits": "yes",
      "consent_to_represent": "yes"
    },
    "first_name": "Jesse",
    "last_name": "Davis",
    "dob": null,
    "ssn": "",
    "last_four": "1133",
    "drivers_license_or_id": "",
    "case_number": "C4158-116",
    "phone_number": "8314207603",
    "alternate_phone_number": "8314207603",
    "email": "cmrtestuser@gmail.com",
    "reasons_for_applying": "['background_check', 'lost_job', 'housing']",
    "how_did_you_hear": "from work",
    "additional_information": "I want help",
    "aliases": "Taylor Brown",
    "pfn_number": "",
    "contact_preferences": "['prefers_email']",
    "preferred_pronouns": "",
    "street": "099 Sawyer Station",
    "city": "Gomezmouth",
    "state": "OR",
    "zip": "38721",
    "us_citizen": "no",
    "is_veteran": "",
    "is_student": "",
    "being_charged": "no",
    "serving_sentence": "no",
    "on_probation_parole": "yes",
    "where_probation_or_parole": "Yolo County",
    "when_probation_or_parole": "2018",
    "finished_half_probation": "",
    "reduced_probation": "",
    "rap_outside_sf": "",
    "when_where_outside_sf": "",
    "has_suspended_license": "",
    "owes_court_fees": "",
    "currently_employed": "",
    "monthly_income": 3625,
    "income_source": "",
    "on_public_benefits": "",
    "owns_home": "",
    "monthly_expenses": null,
    "household_size": null,
    "dependents": 2,
    "is_married": "",
    "has_children": "",
    "old_uuid": "21adb2058539438a81fe2840ab51cbaf",
    "anonymous_name": "Quiet Skyscraper",
    "date_received": "2017-04-22T12:48:43-07:00"
  }
},
{
  "model": "intake.formsubmission",
  "pk": 74,
  "fields": {
    "applicant": 75,
    "duplicate_set": null,
    "answers": {
      "contact_preferences": [
        "prefers_sms"
      ],
      "first_name": "Joseph",
      "middle_name": "Daniel",
      "last_name": "Hughes",
      "aliases": "Angela Spence",
      "phone_number": "8314207603",
      "alternate_phone_number": "8314207603",
      "email": "cmrtestuser@gmail.com",
      "address": {
        "street": "3422 Logan Cliff Suite 709",
        "city": "Krystalfort",
        "state": "PR",
        "zip": "94558"
      },
      "dob": {
        "month": "6",
        "day": "29",
        "year": "1969"
      },
      "driver_license_or_id": "D3216885",
      "last_four": "7462",
      "case_number": "C8719-369",
      "us_citizen": "yes",
      "being_charged": "no",
      "serving_sentence": "no",
      "on_probation_parole": "yes",
      "where_probation_or_parole": "Yolo County",
      "when_probation_or_parole": "2018",
      "monthly_income": 4144,
      "dependents": 4,
      "reasons_for_applying": [
        "background_check",
        "lost_job",
        "housing"
      ],
      "how_did_you_hear": "from work",
      "additional_information": "I want help",
      "understands_limits": "yes",
      "consent_to_represent": "yes"
    },
    "first_name": "Joseph",
    "last_name": "Hughes",
    "dob": null,
    "ssn": "",
    "last_four": "7462",
    "drivers_license_or_id": "",
    "case_number": "C8719-369",
    "phone_number": "8314207603",
    "alternate_phone_number": "8314207603",
    "email": "cmrtestuser@gmail.com",
    "reasons_for_applying": "['background_check', 'lost_job', 'housing']",
    "how_did_you_hear": "from work",
    "additional_information": "I want help",
    "aliases": "Angela Spence",
    "pfn_number": "",
    "contact_preferences": "['prefers_sms']",
    "preferred_pronouns": "",
    "street": "3422 Logan Cliff Suite 709",
    "city": "Krystalfort",
    "state": "PR",
    "zip": "94558",
    "us_citizen": "yes",
    "is_veteran": "",
    "is_student": "",
    "being_charged": "no",
    "serving_sentence": "no",
    "on_probation_parole": "yes",
    "where_probation_or_parole": "Yolo County",
    "when_probation_or_parole": "2018",
    "finished_half_probation": "",
    "reduced_probation": "",
    "rap_outside_sf": "",
    "when_where_outside_sf": "",
    "has_suspended_license": "",
    "owes_court_fees": "",
    "currently_employed": "",
    "monthly_income": 4144,
    "income_source": "",
    "on_public_benefits": "",
    "owns_home": "",
    "monthly_expenses": null,
    "household_size": null,
    "dependents": 4,
    "is_married": "",
    "has_children": "",
    "old_uuid": "0dfb4f9e915a4e21a19d08a00f9a0038",
    "anonymous_name": "Amber Sun",
    "date_received": "2017-04-24T20:25:52-07:00"
  }
},
{
  "model": "intake.application",
  "pk": 103,
  "fields": {
    "created": "2017-04-22T19:48:43Z",
    "updated": "2017-04-25T01:52:08.834Z",
    "organization": [
      "Fresno County Public Defender"
    ],
    "form_submission": 73,
    "was_transferred_out": false
  }
},
{
  "model": "intake.application",
  "pk": 104,
  "fields": {
    "created": "2017-04-25T03:25:52Z",
    "updated": "2017-04-25T01:52:08.860Z",
    "organization": [
      "Fresno County Public Defender"
    ],
    "form_submission": 74,
    "was_transferred_out": false
  }
},
{
  "model": "intake.statusupdate",
  "pk": 104,
  "fields": {
    "created": "2017-04-25T01:52:10.095Z",
    "updated": "2017-04-25T01:52:10.112Z",
    "status_type": 1,
    "additional_information": "We may be able to get a fee waived for you",
    "author": [
      "fresno_pubdef_user"
    ],
    "application": 104,
    "other_next_step": "Come to our Walk-In Clinic",
    "next_steps": [
      1
    ]
  }
},
{
  "model": "intake.statusupdate",
  "pk": 103,
  "fields": {
    "created": "2017-04-25T01:52:10.035Z",
    "updated": "2017-04-25T01:52:10.076Z",
    "status_type": 7,
    "additional_information": "We may be able to get a fee waived for you",
    "author": [
      "fresno_pubdef_user"
    ],
    "application": 103,
    "other_next_step": "Come to our Walk-In Clinic",
    "next_steps": [
      1
    ]
  }
},
{
  "model": "intake.statusnotification",
  "pk": 103,
  "fields": {
    "status_update": 103,
    "contact_info": {
      "email": "cmrtestuser+notification@gmail.com"
    },
    "base_message": "Resistance is futile",
    "sent_message": "Live long and prosper",
    "created": "2017-04-25T01:52:10.041Z"
  }
},
{
  "model": "intake.statusnotification",
  "pk": 104,
  "fields": {
    "status_update": 104,
    "contact_info": {
      "email": "cmrtestuser+notification@gmail.com"
    },
    "base_message": "Resistance is futile",
    "sent_message": "Live long and prosper",
    "created": "2017-04-25T01:52:10.097Z"
  }
}
]
