[
{
  "model": "intake.applicant",
  "pk": 3,
  "fields": {
    "visitor": null
  }
},
{
  "model": "intake.applicant",
  "pk": 4,
  "fields": {
    "visitor": null
  }
},
{
  "model": "intake.formsubmission",
  "pk": 3,
  "fields": {
    "applicant": 3,
    "duplicate_set": null,
    "answers": {
      "owes_court_fees": "no",
      "on_public_benefits": "yes",
      "additional_information": "I want help",
      "when_where_outside_sf": "",
      "us_citizen": "yes",
      "how_did_you_hear": "from work",
      "being_charged": "no",
      "finished_half_probation": "not_applicable",
      "declaration_letter_life_changes": "Saepe accusamus inventore dolorem id magni consequatur. Saepe itaque repellat nihil quaerat quisquam. At eveniet repudiandae eveniet repellat cupiditate minima. Quisquam nobis perspiciatis ea temporibus ea.",
      "consent_to_represent": "yes",
      "reduced_probation": "not_applicable",
      "middle_name": "Dorothy",
      "declaration_letter_goals": "Tempora neque ratione adipisci porro sint minima. Eius recusandae illo iusto minus rem. Vitae cumque neque adipisci sunt ducimus.",
      "first_name": "Philip",
      "understands_limits": "yes",
      "has_suspended_license": "no",
      "contact_preferences": [
        "prefers_email",
        "prefers_snailmail",
        "prefers_voicemail"
      ],
      "phone_number": "2881784213",
      "address": {
        "street": "6699 Sims Streets",
        "zip": "69602",
        "state": "TN",
        "city": "Craigchester"
      },
      "serving_sentence": "no",
      "declaration_letter_why": "Id perspiciatis pariatur fugiat perferendis. Quasi quos animi eligendi debitis iure. Repellat omnis facere quia beatae corrupti officiis eaque. Soluta autem error magnam.",
      "household_size": 1,
      "on_probation_parole": "yes",
      "monthly_income": 2999,
      "rap_outside_sf": "no",
      "dob": {
        "day": "8",
        "month": "2",
        "year": "1967"
      },
      "owns_home": "no",
      "declaration_letter_activities": "Deserunt natus praesentium temporibus. Expedita distinctio fugiat optio distinctio. Impedit ipsum veniam repellat hic. Expedita sint atque repellendus ullam quae iure inventore.",
      "email": "robertsonjeffrey@yahoo.com",
      "declaration_letter_intro": "Labore blanditiis deleniti error est architecto neque. Distinctio molestiae error saepe sed necessitatibus. Eius at accusamus eos eum.",
      "preferred_pronouns": "",
      "last_name": "Holland",
      "alternate_phone_number": "2278877193"
    },
    "old_uuid": "20afbf8d7d99412588aeb57239be5cb8",
    "anonymous_name": "Golden Gerbil",
    "date_received": "2017-02-02T02:56:30-08:00"
  }
},
{
  "model": "intake.formsubmission",
  "pk": 4,
  "fields": {
    "applicant": 4,
    "duplicate_set": null,
    "answers": {
      "owes_court_fees": "yes",
      "on_public_benefits": "yes",
      "additional_information": "I want help",
      "when_where_outside_sf": "",
      "us_citizen": "yes",
      "how_did_you_hear": "from work",
      "being_charged": "yes",
      "finished_half_probation": "not_applicable",
      "declaration_letter_life_changes": "Maiores quisquam iste quas officia. Totam illum cum aspernatur ratione fugit. Harum occaecati temporibus aspernatur eius eligendi.",
      "consent_to_represent": "yes",
      "reduced_probation": "not_applicable",
      "middle_name": "Vincent",
      "declaration_letter_goals": "Esse dignissimos voluptas asperiores doloremque. Accusamus sapiente dicta fugiat culpa quasi doloremque. Doloribus quisquam quaerat error explicabo porro quia. Accusantium aliquam voluptate illo ex aliquam sed.",
      "first_name": "Amanda",
      "understands_limits": "yes",
      "has_suspended_license": "no",
      "contact_preferences": [
        "prefers_sms",
        "prefers_voicemail",
        "prefers_email"
      ],
      "phone_number": "2823095410",
      "address": {
        "street": "5620 Tiffany Island",
        "zip": "07824",
        "state": "AZ",
        "city": "Maryberg"
      },
      "serving_sentence": "no",
      "declaration_letter_why": "Fugit ut eum consequatur saepe. Iste est dolore inventore laudantium. Quam velit assumenda nisi odit at.",
      "household_size": 3,
      "on_probation_parole": "yes",
      "monthly_income": 2999,
      "rap_outside_sf": "no",
      "dob": {
        "day": "28",
        "month": "10",
        "year": "1992"
      },
      "owns_home": "no",
      "declaration_letter_activities": "Totam aliquam tempora voluptatibus cum animi quasi. Iure possimus fugiat commodi minus. Ab iste quisquam mollitia officia soluta illum.",
      "email": "cannonvanessa@hotmail.com",
      "declaration_letter_intro": "Quisquam laborum officia beatae neque ab doloribus nobis. Dolor mollitia suscipit perferendis fugit facilis. Consequatur nobis quis quaerat perferendis voluptates.",
      "preferred_pronouns": "",
      "last_name": "Shah",
      "alternate_phone_number": "2766442351"
    },
    "old_uuid": "5e4bf28d94c348ae896ab018289051b8",
    "anonymous_name": "Crimson Tree",
    "date_received": "2017-02-01T04:13:29-08:00"
  }
},
{
  "model": "intake.application",
  "pk": 3,
  "fields": {
    "organization": [
      "Alameda County Public Defender's Office"
    ],
    "form_submission": 3
  }
},
{
  "model": "intake.application",
  "pk": 4,
  "fields": {
    "organization": [
      "Alameda County Public Defender's Office"
    ],
    "form_submission": 4
  }
},
{
  "model": "intake.statusupdate",
  "pk": 3,
  "fields": {
    "created": "2017-02-10T23:37:13.557Z",
    "updated": "2017-02-10T23:37:13.563Z",
    "status_type": 3,
    "additional_information": "We may be able to get a fee waived for you",
    "author": [
      "a_pubdef_user"
    ],
    "application": 3,
    "other_next_step": "Come to our Walk-In Clinic",
    "next_steps": [
      1
    ]
  }
},
{
  "model": "intake.statusupdate",
  "pk": 4,
  "fields": {
    "created": "2017-02-10T23:37:13.578Z",
    "updated": "2017-02-10T23:37:13.587Z",
    "status_type": 4,
    "additional_information": "We may be able to get a fee waived for you",
    "author": [
      "a_pubdef_user"
    ],
    "application": 4,
    "other_next_step": "Come to our Walk-In Clinic",
    "next_steps": [
      1
    ]
  }
},
{
  "model": "intake.statusnotification",
  "pk": 3,
  "fields": {
    "status_update": 3,
    "contact_info": {
      "email": "bgolder+borg@codeforamerica.org"
    },
    "base_message": "Resistance is futile",
    "sent_message": "Live long and prosper",
    "created": "2017-02-10T23:37:14.333Z"
  }
},
{
  "model": "intake.statusnotification",
  "pk": 4,
  "fields": {
    "status_update": 4,
    "contact_info": {
      "email": "bgolder+borg@codeforamerica.org"
    },
    "base_message": "Resistance is futile",
    "sent_message": "Live long and prosper",
    "created": "2017-02-10T23:37:14.340Z"
  }
}
]
